aliyunsdkworkbench_ide/__init__.py
aliyunsdkworkbench_ide/request/__init__.py
aliyunsdkworkbench_ide/request/v20210121/AddAppDeveloperRequest.py
aliyunsdkworkbench_ide/request/v20210121/AddAppRequest.py
aliyunsdkworkbench_ide/request/v20210121/AddEnvironmentRequest.py
aliyunsdkworkbench_ide/request/v20210121/AddOrgMemberRequest.py
aliyunsdkworkbench_ide/request/v20210121/AddProductRequest.py
aliyunsdkworkbench_ide/request/v20210121/AddSolutionRequest.py
aliyunsdkworkbench_ide/request/v20210121/DeleteAppRequest.py
aliyunsdkworkbench_ide/request/v20210121/DeleteEnvironmentRequest.py
aliyunsdkworkbench_ide/request/v20210121/DeleteSolutionRequest.py
aliyunsdkworkbench_ide/request/v20210121/DeployAppRequest.py
aliyunsdkworkbench_ide/request/v20210121/EditAppRequest.py
aliyunsdkworkbench_ide/request/v20210121/EditEnvironmentRequest.py
aliyunsdkworkbench_ide/request/v20210121/EditProductRequest.py
aliyunsdkworkbench_ide/request/v20210121/EditSolutionRequest.py
aliyunsdkworkbench_ide/request/v20210121/GetAppApiGatewayAppRequest.py
aliyunsdkworkbench_ide/request/v20210121/GetAppApiGatewayGroupRequest.py
aliyunsdkworkbench_ide/request/v20210121/GetAppDeployDomainRequest.py
aliyunsdkworkbench_ide/request/v20210121/GetAppDeployLogRequest.py
aliyunsdkworkbench_ide/request/v20210121/GetAppDeployRequest.py
aliyunsdkworkbench_ide/request/v20210121/GetAppEnvConfigRequest.py
aliyunsdkworkbench_ide/request/v20210121/GetAppGlobalConfigRequest.py
aliyunsdkworkbench_ide/request/v20210121/GetAppPackageUploadUrlRequest.py
aliyunsdkworkbench_ide/request/v20210121/GetAppRepositoryRequest.py
aliyunsdkworkbench_ide/request/v20210121/GetAppRequest.py
aliyunsdkworkbench_ide/request/v20210121/GetEnvironmentRequest.py
aliyunsdkworkbench_ide/request/v20210121/GetSolutionEnvRequest.py
aliyunsdkworkbench_ide/request/v20210121/GetSolutionRelyServiceRequest.py
aliyunsdkworkbench_ide/request/v20210121/GetSolutionRepoRequest.py
aliyunsdkworkbench_ide/request/v20210121/GetSolutionRequest.py
aliyun_python_sdk_workbench_ide-2.0.5.dist-info/LICENSE
aliyun_python_sdk_workbench_ide-2.0.5.dist-info/METADATA
aliyun_python_sdk_workbench_ide-2.0.5.dist-info/WHEEL
aliyun_python_sdk_workbench_ide-2.0.5.dist-info/top_level.txt
aliyun_python_sdk_workbench_ide-2.0.5.dist-info/RECORD
